LICENSE
MANIFEST.in
README.rst
setup.cfg
setup.py
django_address/__init__.py
django_address/admin.py
django_address/apps.py
django_address/models.py
django_address/utils.py
django_address/fixtures/countries-code.json
django_address/fixtures/countries.json
django_address/fixtures/languages/id/addresses.json
django_address/management/__init__.py
django_address/management/commands/__init__.py
django_address/management/commands/create_address.py
django_address/migrations/0001_initial.py
django_address/migrations/__init__.py
django_address/tests/__init__.py
django_address/tests/test_models.py
django_address_model.egg-info/PKG-INFO
django_address_model.egg-info/SOURCES.txt
django_address_model.egg-info/dependency_links.txt
django_address_model.egg-info/not-zip-safe
django_address_model.egg-info/requires.txt
django_address_model.egg-info/top_level.txt