Metadata-Version: 1.1
Name: django-address-model
Version: 1.0.4
Summary: Django Address Model
Home-page: https://github.com/agusmakmun/django-address-model
Author: Agus Makmun (Summon Agus)
Author-email: summon.agus@gmail.com
License: MIT
Download-URL: https://github.com/agusmakmun/django-address-model/tarball/v1.0.4
Keywords: django address,django address model
Platform: UNKNOWN
Classifier: Framework :: Django
Classifier: Framework :: Django :: 1.8
Classifier: Framework :: Django :: 1.9
Classifier: Framework :: Django :: 1.10
Classifier: Framework :: Django :: 1.11
Classifier: Intended Audience :: Developers
Classifier: Operating System :: OS Independent
Classifier: Programming Language :: Python
Classifier: Programming Language :: Python :: 2.7
Classifier: Programming Language :: Python :: 3.4
Classifier: Programming Language :: Python :: 3.5
Classifier: Programming Language :: Python :: 3.6
Classifier: Programming Language :: Python :: 3.7
Classifier: Development Status :: 5 - Production/Stable
Classifier: Topic :: Software Development :: Libraries :: Python Modules
Classifier: License :: OSI Approved :: MIT License
Classifier: Environment :: Web Environment
